{
  "layoutId": "layout-998",
  "apartment": {
    "id": "apartment-998",
    "name": "Sample K",
    "geometry": [
      [
        10.15,
        3.75
      ],
      [
        7.1,
        3.75
      ],
      [
        4.15,
        3.75
      ],
      [
        4.15,
        5.2
      ],
      [
        2.15,
        5.2
      ],
      [
        2.15,
        6.45
      ],
      [
        2.15,
        7.75
      ],
      [
        4.15,
        7.75
      ],
      [
        6.35,
        7.75
      ],
      [
        6.35,
        9.1
      ],
      [
        7.1,
        9.1
      ],
      [
        10.15,
        9.1
      ],
      [
        10.15,
        6.35
      ],
      [
        10.15,
        3.75
      ]
    ],
    "attributes": {
      "area": 34.23,
      "description": "1 kitchen, 1 bath, 2 bed, 1 balcony, 1 storage, 1 living."
    }
  },
  "outline": [
    [
      10.15,
      3.75
    ],
    [
      7.1,
      3.75
    ],
    [
      4.15,
      3.75
    ],
    [
      4.15,
      5.2
    ],
    [
      2.15,
      5.2
    ],
    [
      2.15,
      6.45
    ],
    [
      2.15,
      7.75
    ],
    [
      4.15,
      7.75
    ],
    [
      6.35,
      7.75
    ],
    [
      6.35,
      9.1
    ],
    [
      7.1,
      9.1
    ],
    [
      10.15,
      9.1
    ],
    [
      10.15,
      6.35
    ],
    [
      10.15,
      3.75
    ]
  ],
  "rooms": [
    {
      "id": "room-1",
      "name": "Kitchen",
      "geometry": [
        [
          2.15,
          7.75
        ],
        [
          2.15,
          6.45
        ],
        [
          4.15,
          6.45
        ],
        [
          4.15,
          7.75
        ],
        [
          2.15,
          7.75
        ]
      ],
      "attributes": {
        "area": 2.6,
        "program": "kitchen"
      }
    },
    {
      "id": "room-2",
      "name": "Bath",
      "geometry": [
        [
          2.15,
          5.2
        ],
        [
          4.15,
          5.2
        ],
        [
          4.15,
          6.45
        ],
        [
          2.15,
          6.45
        ],
        [
          2.15,
          5.2
        ]
      ],
      "attributes": {
        "area": 2.5,
        "program": "bath"
      }
    },
    {
      "id": "room-3",
      "name": "Bed",
      "geometry": [
        [
          7.1,
          3.75
        ],
        [
          10.15,
          3.75
        ],
        [
          10.15,
          6.35
        ],
        [
          7.1,
          6.35
        ],
        [
          7.1,
          3.75
        ]
      ],
      "attributes": {
        "area": 7.93,
        "program": "bed"
      }
    },
    {
      "id": "room-4",
      "name": "Bed",
      "geometry": [
        [
          10.15,
          6.35
        ],
        [
          10.15,
          9.1
        ],
        [
          7.1,
          9.1
        ],
        [
          7.1,
          6.35
        ],
        [
          10.15,
          6.35
        ]
      ],
      "attributes": {
        "area": 8.39,
        "program": "bed"
      }
    },
    {
      "id": "room-6",
      "name": "Storage",
      "geometry": [
        [
          6.35,
          7.75
        ],
        [
          7.1,
          7.75
        ],
        [
          7.1,
          9.1
        ],
        [
          6.35,
          9.1
        ],
        [
          6.35,
          7.75
        ]
      ],
      "attributes": {
        "area": 1.01,
        "program": "storage"
      }
    },
    {
      "id": "room-7",
      "name": "Living",
      "geometry": [
        [
          4.15,
          3.75
        ],
        [
          7.1,
          3.75
        ],
        [
          7.1,
          7.75
        ],
        [
          4.15,
          7.75
        ],
        [
          4.15,
          3.75
        ]
      ],
      "attributes": {
        "area": 11.8,
        "program": "living"
      }
    }
  ],
  "doors": [
    {
      "id": "door-1",
      "name": "Door 1",
      "geometry": [
        [
          4.15,
          7.1
        ]
      ],
      "attributes": {
        "connectsRooms": [
          "room-1",
          "room-7"
        ]
      }
    },
    {
      "id": "door-2",
      "name": "Door 2",
      "geometry": [
        [
          4.15,
          5.825
        ]
      ],
      "attributes": {
        "connectsRooms": [
          "room-2",
          "room-7"
        ]
      }
    },
    {
      "id": "door-3",
      "name": "Door 3",
      "geometry": [
        [
          7.1,
          5.05
        ]
      ],
      "attributes": {
        "connectsRooms": [
          "room-3",
          "room-7"
        ]
      }
    },
    {
      "id": "door-4",
      "name": "Door 4",
      "geometry": [
        [
          7.1,
          7.05
        ]
      ],
      "attributes": {
        "connectsRooms": [
          "room-4",
          "room-7"
        ]
      }
    },
    {
      "id": "door-6",
      "name": "Door 6",
      "geometry": [
        [
          6.725,
          7.75
        ]
      ],
      "attributes": {
        "connectsRooms": [
          "room-6",
          "room-7"
        ]
      }
    }
  ],
  "facades": [
    {
      "id": "facade-1",
      "name": "Facade 1",
      "geometry": [
        [
          10.15,
          3.75
        ],
        [
          7.1,
          3.75
        ],
        [
          4.15,
          3.75
        ],
        [
          4.15,
          5.2
        ],
        [
          2.15,
          5.2
        ],
        [
          2.15,
          6.45
        ],
        [
          2.15,
          7.75
        ],
        [
          4.15,
          7.75
        ]
      ],
      "attributes": {
        "type": "exterior",
        "length": 14.0
      }
    },
    {
      "id": "facade-2",
      "name": "Facade 2",
      "geometry": [
        [
          6.35,
          7.75
        ],
        [
          6.35,
          9.1
        ],
        [
          7.1,
          9.1
        ],
        [
          10.15,
          9.1
        ],
        [
          10.15,
          6.35
        ],
        [
          10.15,
          3.75
        ]
      ],
      "attributes": {
        "type": "exterior",
        "length": 10.5
      }
    }
  ],
  "circulation": [
    {
      "id": "circulation-1",
      "name": "Front Door Axis",
      "geometry": [
        [
          6.35,
          7.75
        ],
        [
          4.15,
          7.75
        ]
      ],
      "attributes": {
        "type": "circulation",
        "length": 2.1999999999999993
      }
    }
  ],
  "windows": [],
  "furniture": [],
  "mep": [],
  "structure": []
}